apply_pr/__init__.py
apply_pr/changelog.py
apply_pr/cli.py
apply_pr/exceptions.py
apply_pr/fabfile.py
apply_pr/github_utils.py
apply_pr/version.py
apply_pr-3.4.0.dist-info/METADATA
apply_pr-3.4.0.dist-info/WHEEL
apply_pr-3.4.0.dist-info/entry_points.txt
apply_pr-3.4.0.dist-info/top_level.txt
apply_pr-3.4.0.dist-info/RECORD
