Metadata-Version: 2.1
Name: apply-pr
Version: 3.4.0
Summary: Apply Pull Requests from GitHub
Home-page: https://github.com/gisce/apply_pr
Author: GISCE-TI, S.L.
Author-email: devel@gisce.net
License: MIT
Platform: UNKNOWN
Requires-Dist: six
Requires-Dist: fabric (<2.0)
Requires-Dist: paramiko (<2.10)
Requires-Dist: osconf
Requires-Dist: python-slugify (<6)
Requires-Dist: requests
Requires-Dist: click
Requires-Dist: tqdm
Requires-Dist: packaging
Requires-Dist: giscemultitools (>=1.1.0)
Requires-Dist: qrcode
Requires-Dist: importlib-metadata ; python_version < "3.8"
